flexpoolapi/__init__.py
flexpoolapi/exceptions.py
flexpoolapi/minerapi.py
flexpoolapi/poolapi.py
flexpoolapi/shared.py
flexpoolapi/utils.py
flexpoolapi/workerapi.py
flexpoolapi-1.2.7.post2.dist-info/LICENSE
flexpoolapi-1.2.7.post2.dist-info/METADATA
flexpoolapi-1.2.7.post2.dist-info/WHEEL
flexpoolapi-1.2.7.post2.dist-info/top_level.txt
flexpoolapi-1.2.7.post2.dist-info/RECORD
