Metadata-Version: 2.1
Name: flexpoolapi
Version: 1.2.7.post2
Summary: 🐍 Pythonic wrapper for Flexpool Public API
Home-page: https://github.com/flexpool/py-flexpoolapi
Author: Flexpool
Author-email: office@flexpool.io
License: UNKNOWN
Platform: UNKNOWN
Classifier: Programming Language :: Python :: 3
Classifier: License :: OSI Approved :: MIT License
Classifier: Operating System :: OS Independent
Requires-Python: >=3.6
Requires-Dist: requests
Requires-Dist: si-prefix
